soulless_ai_dem/__init__.py
soulless_ai_dem/demotivator.py
soulless_ai_dem/fonts/times.ttf
soulless_ai_dem/templates/base.jpg
soulless_ai_dem/templates/base.png
soulless_ai_dem/templates/base_r.jpg
soulless_ai_dem/templates/base_r.png
SoullessAi_Dem-1.1.4.4.dist-info/METADATA
SoullessAi_Dem-1.1.4.4.dist-info/WHEEL
SoullessAi_Dem-1.1.4.4.dist-info/top_level.txt
SoullessAi_Dem-1.1.4.4.dist-info/RECORD
